lucie/__init__.py
lucie/import_fns.py
lucie-1.0.2.dist-info/METADATA
lucie-1.0.2.dist-info/WHEEL
lucie-1.0.2.dist-info/licenses/LICENSE
lucie-1.0.2.dist-info/RECORD
