Metadata-Version: 2.3
Name: lucie
Version: 1.0.2
Summary: A package that will automatically determine the dataset scheme/format for a UCI dataset, and import it to the best of its ability. Preserves the UCI Python import API. Please see https://github.com/ArnaoutLab/Lucie
Project-URL: Homepage, https://github.com/ArnaoutLab/Lucie
Project-URL: Issues, https://github.com/ArnaoutLab/Lucie/issues
Author-email: Kenneth Ge <kennethkouge@gmail.com>, Phuc Nguyen <pnguye10@bidmc.harvard.edu>, Ramy Arnaout <rarnaout@bidmc.harvard.edu>
License-File: LICENSE
Classifier: License :: OSI Approved :: MIT License
Classifier: Operating System :: OS Independent
Classifier: Programming Language :: Python :: 3
Requires-Python: >=3.8
